# Goal

자바 소스 파일(.java)을 JVM으로 실행하는 과정 이해하기.

# 목차

- JVM이란 무엇인가
- 컴파일 하는 방법
- 실행하는 방법
- 바이트코드란 무엇인가
- JIT 컴파일러란 무엇이며 어떻게 동작하는지
- JVM 구성 요소
- JDK와 JRE의 차이

## JVM이란 무엇인가

> Java Virtual Machine : 자바 소스를 컴파일한 산출물인 class 파일을 실행하는 가상의 컴퓨터.
> 운영체제가 달라도 JVM 이 지원된다면 컴파일 다시하지 않고 프로그램 실행 가능함

> C / C++ 의 경우 운영체제가 달라지면 컴파일을 다시해야하며 , 경우에 따라서는 소스 코드(운영체제나 하드웨어가 지원하는 변수 사이즈 차이등)를 수정해야하는 경우도 발생함

> MyProgram.java 를 컴파일하면 MyProgram.class 파일이 생성된다.

https://docs.oracle.com/javase/tutorial/getStarted/intro/definition.html

## 컴파일 하는 방법, 실행하는 방법

> 자바 프로그램을 만들고 실행하기 위한 환경설정
>
> 1. JDK 를 설치
> 2. VSCode, Intellij, Eclipse 같은 코딩을 위한 도구가 설치되어야 한다.

> 자바 프로그램 실행 과정
>
> 1. 소스 파일 생성
> 2. 컴파일
> 3. 실행

```
/**
 * Hello world 프로그램
 * C:\Users\angora\source> 에 HelloWorldApp.java 라는 이름으로 파일 저장함
 */
class HelloWorldApp {
    public static void main(String[] args) {
        System.out.println("Hello World!"); // 문자열을 출력한다.
    }
}
```

```
C:\Users\angora\source>javac HelloWorldApp.java

C:\Users\angora\source>java HelloWorldApp
Hello World!
C:\Users\angora\source>
```

https://docs.oracle.com/javase/tutorial/getStarted/cupojava/win32.html

## 바이트코드란 무엇인가

> 자바 가상 머신이 실행하는 명령어의 형태이다. C / C++ 의 어셈블러와 같다.

> 자바바이트 코드를 보기위해서는 javap 명령어를 사용한다.

```
C:\Users\angora\source>javap -v HelloWorldApp.class
Classfile /C:/Users/angora/source/HelloWorldApp.class
  Last modified 2021. 2. 26.; size 432 bytes
  MD5 checksum 58a6495e03daee25ff926517d29790bb
  Compiled from "HelloWorldApp.java"
class HelloWorldApp
  minor version: 0
  major version: 55
  flags: (0x0020) ACC_SUPER
  this_class: #5                          // HelloWorldApp
  super_class: #6                         // java/lang/Object
  interfaces: 0, fields: 0, methods: 2, attributes: 1
Constant pool:
   #1 = Methodref          #6.#15         // java/lang/Object."<init>":()V
   #2 = Fieldref           #16.#17        // java/lang/System.out:Ljava/io/PrintStream;
   #3 = String             #18            // Hello World!
   #4 = Methodref          #19.#20        // java/io/PrintStream.println:(Ljava/lang/String;)V
   #5 = Class              #21            // HelloWorldApp
   #6 = Class              #22            // java/lang/Object
   #7 = Utf8               <init>
   #8 = Utf8               ()V
   #9 = Utf8               Code
  #10 = Utf8               LineNumberTable
  #11 = Utf8               main
  #12 = Utf8               ([Ljava/lang/String;)V
  #13 = Utf8               SourceFile
  #14 = Utf8               HelloWorldApp.java
  #15 = NameAndType        #7:#8          // "<init>":()V
  #16 = Class              #23            // java/lang/System
  #17 = NameAndType        #24:#25        // out:Ljava/io/PrintStream;
  #18 = Utf8               Hello World!
  #19 = Class              #26            // java/io/PrintStream
  #20 = NameAndType        #27:#28        // println:(Ljava/lang/String;)V
  #21 = Utf8               HelloWorldApp
  #22 = Utf8               java/lang/Object
  #23 = Utf8               java/lang/System
  #24 = Utf8               out
  #25 = Utf8               Ljava/io/PrintStream;
  #26 = Utf8               java/io/PrintStream
  #27 = Utf8               println
  #28 = Utf8               (Ljava/lang/String;)V
{
  HelloWorldApp();
    descriptor: ()V
    flags: (0x0000)
    Code:
      stack=1, locals=1, args_size=1
         0: aload_0
         1: invokespecial #1                  // Method java/lang/Object."<init>":()V
         4: return
      LineNumberTable:
        line 1: 0

  public static void main(java.lang.String[]);
    descriptor: ([Ljava/lang/String;)V
    flags: (0x0009) ACC_PUBLIC, ACC_STATIC
    Code:
      stack=2, locals=1, args_size=1
         0: getstatic     #2                  // Field java/lang/System.out:Ljava/io/PrintStream;
         3: ldc           #3                  // String Hello World!
         5: invokevirtual #4                  // Method java/io/PrintStream.println:(Ljava/lang/String;)V
         8: return
      LineNumberTable:
        line 3: 0
        line 4: 8
}
SourceFile: "HelloWorldApp.java"

C:\Users\angora\source>
```

https://ko.wikipedia.org/wiki/%EC%9E%90%EB%B0%94_%EB%B0%94%EC%9D%B4%ED%8A%B8%EC%BD%94%EB%93%9C

https://www.ibm.com/developerworks/library/it-haggar_bytecode/

## JIT 컴파일러란 무엇이며 어떻게 동작하는지

> 컴퓨터 프로그램을 소스코드에서 만드는 방법은 컴파일, 인터프리터 2가지 방식이 있다.

> JIT 컴파일은 컴파일, 인터프리터 2가지 방식을 혼용하여 효율을 높인 방식이다.

> 바이트코드 컴파일러는 소스 코드를 중간언어인 바이트코드로 변환한다. 바이트코드는 가상 머신에 의해 기계어로 손쉽게 변환할 수 있는 코드이다. JIT 컴파일러는 바이트코드를 읽어 빠른 속도로 기계어를 생성할 수 있다. 기계어 변환은 코드가 실행되는 과정에 실시간으로 일어나며(그래서 Just-In-Time이다), 전체 코드의 필요한 부분만 변환한다. 기계어로 변환된 코드는 캐시에 저장되기 때문에 재사용시 컴파일을 다시 할 필요가 없다.

> 인터프러터 언어는 바이트코드나 소스코드에 대한 최적화 과정 없이 번역하기 때문에 성능이 낮다. 반면 C / C++ 언어는 플랫폼 변경시 반드시 컴파일을 해야하기 때문에 시간이 오래 걸린다. 동적 컴파일 환경은 실행 과정에서 컴파일을 할 수 있기 위해 만들어졌다. JIT는 정적 컴파일러 만큼 빠르면서 인터프러터 언어의 빠른 응답속도를 추구하기 위해 사용한다. 바이트코드 컴파일러에서 시간이 많이 소요되는 최적화를 미리 해주기 때문에 바이트코드에서 기계어 번역은 훨씬 빠르게 진행될 수 있다. 또한 바이트코드는 이식성이 뛰어나 가상 머신이 설치되어 있으면 빠르게 실행할 수 있다.

https://ko.wikipedia.org/wiki/JIT_%EC%BB%B4%ED%8C%8C%EC%9D%BC

https://aboullaite.me/understanding-jit-compiler-just-in-time-compiler/

## JVM 구성 요소

> 클래스 로더 시스템
> .class 파일에서 바이트코드를 읽고 메모리에 저장
> 로딩 : 클래스 읽어오는 과정
> 링크 : 레퍼런스를 연결하는 과정
> 초기화 : static 값 초기화 및 변수 할당

> 메모리
> 메모리 영역에는 클래스 수준의 정보(클래스 이름, 부모 클래스 이름, 메소드, 변수) 저장,공유자원
> 힙 : 객체를 저장, 공유자원
> 스택 : 스레드 마다 런타임 스택을 만들고, 그안에 메소드 호출을 스택 프레임이라 부르는 블럭으로 쌓는다. 스레드 종료시 런타임 스택도 사라짐
> PC 레지스터 : 스레드 마다 현재 실행할 스택 프레임을 가리키는 포인터가 생성된다.

> 실행엔진
> 인터프리터 : 바이트코드를 한줄씩 실행
> JIT 컴파일러 : 인터프리터 효율을 높이기 위해 반복되는 코드를 네이티브 코드로 바꾸둔다. 다음부터 반복되는 코드는 네이티브로 컴파일된 코드를 바로 사용한다.
> GC(Garbage Collector) : 더이상 참조되지 않는 객체를 모아서 정리한다.

> JNI (Java Native Interface)
> 자바 프로그램에서 C, C++, ASM 으로 작성된 함수를 사용할 수 있는 방법을 제공

> 네이티브 메소드 라이브러리
> C, C++ 로 작성된 라이브러리

https://www.inflearn.com/course/the-java-code-manipulation

## JDK와 JRE의 차이

> JVM : Java Virtual Machine
> 자바 가상머신 : 자바 바이트코드를 기계어로 변환하여 실행한다.

> JRE : Java Runtime Environment = JVM + Library
> 자바 프로그램을 실행할수 있도록 구성된 배포판

> JDK : Java Development Kit = JRE + Java Development tools

https://www.inflearn.com/course/the-java-code-manipulation
